sidious/__init__.py
sidious-0.0.1.dist-info/METADATA
sidious-0.0.1.dist-info/WHEEL
sidious-0.0.1.dist-info/top_level.txt
sidious-0.0.1.dist-info/RECORD
